basico/__init__.py
basico/_version.py
basico/biomodels.py
basico/callbacks.py
basico/compartment_array_tools.py
basico/expressions.py
basico/jws_online.py
basico/logging.py
basico/model_info.py
basico/model_io.py
basico/processing.py
basico/task_lna.py
basico/task_lyapunov.py
basico/task_mca.py
basico/task_optimization.py
basico/task_parameterestimation.py
basico/task_profile_likelihood.py
basico/task_scan.py
basico/task_sensitivities.py
basico/task_steadystate.py
basico/task_timecourse.py
basico/data/BIOM10-fit.cps
basico/data/CircadianClock.cps
basico/data/DimericMWC-stiff.cps
basico/data/Genetic-2000Elo.xml
basico/data/LM-test1.cps
basico/data/MAPK-HF96-layout.cps
basico/data/MAPKdata.txt
basico/data/NF-kappaB.cps
basico/data/Olsen2003_peroxidase.cps
basico/data/PK_fit2.cps
basico/data/YeastGlycolysis.cps
basico/data/YeastGlycolysis.gps
basico/data/array_1d.cps
basico/data/brusselator.cps
basico/data/data_2.txt
basico/data/data_3.txt
basico/data/linear_base.cps
basico/data/mmspect3.txt
basico/data/turing_base.cps
basico/petab/__init__.py
basico/petab/core.py
basico/petab/select.py
copasi_basico-0.86.dist-info/licenses/LICENSE
copasi_basico-0.86.dist-info/METADATA
copasi_basico-0.86.dist-info/WHEEL
copasi_basico-0.86.dist-info/top_level.txt
copasi_basico-0.86.dist-info/RECORD
