Metadata-Version: 2.4
Name: copasi_basico
Version: 0.86
Summary: Simplified COPASI interface for python
Home-page: https://github.com/copasi/basico
Author: COPASI Team
Author-email: developers@copasi.org
License: Artistic-2.0
Project-URL: Github, https://github.com/copasi/basico
Project-URL: Issues, https://github.com/copasi/basico/issues
Project-URL: Try it online, https://colab.research.google.com/github/copasi/basico/blob/master/docs/notebooks/index_colab.ipynb
Keywords: copasi sbml systems biology
Platform: Windows
Platform: Linux
Platform: MacOS
Classifier: Topic :: Scientific/Engineering :: Bio-Informatics
Classifier: Development Status :: 5 - Production/Stable
Classifier: License :: OSI Approved :: Artistic License
Classifier: Intended Audience :: Science/Research
Classifier: Intended Audience :: Education
Classifier: Natural Language :: English
Classifier: Operating System :: MacOS :: MacOS X
Classifier: Operating System :: Microsoft :: Windows
Classifier: Operating System :: POSIX :: Linux
Classifier: Programming Language :: C++
Classifier: Programming Language :: Python :: 3
Classifier: Programming Language :: Python :: 3.9
Classifier: Programming Language :: Python :: 3.10
Classifier: Programming Language :: Python :: 3.11
Classifier: Programming Language :: Python :: 3.12
Classifier: Programming Language :: Python :: 3.13
Classifier: Programming Language :: Python :: Implementation :: CPython
Classifier: Programming Language :: Python :: Implementation :: PyPy
License-File: LICENSE
Requires-Dist: python-copasi
Requires-Dist: pandas
Requires-Dist: numpy
Requires-Dist: matplotlib
Requires-Dist: PyYAML
Requires-Dist: scipy
Requires-Dist: lxml
Provides-Extra: petab
Requires-Dist: copasi-petab-importer; extra == "petab"
Requires-Dist: petab; extra == "petab"
Requires-Dist: petab-select; extra == "petab"
Provides-Extra: tqdm
Requires-Dist: tqdm; extra == "tqdm"
Provides-Extra: docs
Requires-Dist: sphinx; extra == "docs"
Requires-Dist: sphinx_rtd_theme; extra == "docs"
Requires-Dist: sphinxcontrib-bibtex; extra == "docs"
Requires-Dist: sphinxcontrib-programoutput; extra == "docs"
Requires-Dist: sphinxcontrib-mermaid; extra == "docs"
Requires-Dist: sphinxcontrib-plantuml; extra == "docs"
Requires-Dist: sphinxcontrib; extra == "docs"
Provides-Extra: ssr
Requires-Dist: libssr; extra == "ssr"
Requires-Dist: python-libsbml; extra == "ssr"
Dynamic: author
Dynamic: author-email
Dynamic: classifier
Dynamic: description
Dynamic: description-content-type
Dynamic: home-page
Dynamic: keywords
Dynamic: license
Dynamic: license-file
Dynamic: platform
Dynamic: project-url
Dynamic: provides-extra
Dynamic: requires-dist
Dynamic: summary
